{ "columns":20,
 "image":"..\/..\/..\/public\/level\/grid_floor.png",
 "imageheight":1536,
 "imagewidth":2048,
 "margin":0,
 "name":"tiled_room_tiled",
 "spacing":0,
 "tilecount":300,
 "tileheight":100,
 "tileproperties":
    {
     "0":
        {
         "wall":null
        },
     "1":
        {
         "wall":null
        },
     "10":
        {
         "wall":null
        },
     "100":
        {
         "wall":null
        },
     "101":
        {
         "wall":true
        },
     "102":
        {
         "wall":null
        },
     "103":
        {
         "wall":null
        },
     "104":
        {
         "wall":null
        },
     "105":
        {
         "wall":null
        },
     "106":
        {
         "wall":null
        },
     "107":
        {
         "wall":null
        },
     "108":
        {
         "wall":true
        },
     "109":
        {
         "wall":null
        },
     "11":
        {
         "wall":null
        },
     "110":
        {
         "wall":null
        },
     "111":
        {
         "wall":null
        },
     "112":
        {
         "wall":null
        },
     "113":
        {
         "wall":null
        },
     "114":
        {
         "wall":null
        },
     "115":
        {
         "wall":null
        },
     "116":
        {
         "wall":null
        },
     "117":
        {
         "wall":null
        },
     "118":
        {
         "wall":true
        },
     "119":
        {
         "wall":null
        },
     "12":
        {
         "wall":null
        },
     "120":
        {
         "wall":null
        },
     "121":
        {
         "wall":true
        },
     "122":
        {
         "wall":null
        },
     "123":
        {
         "wall":null
        },
     "124":
        {
         "wall":null
        },
     "125":
        {
         "wall":null
        },
     "126":
        {
         "wall":null
        },
     "127":
        {
         "wall":null
        },
     "128":
        {
         "wall":true
        },
     "129":
        {
         "wall":null
        },
     "13":
        {
         "wall":null
        },
     "130":
        {
         "wall":null
        },
     "131":
        {
         "wall":null
        },
     "132":
        {
         "wall":null
        },
     "133":
        {
         "wall":null
        },
     "134":
        {
         "wall":null
        },
     "135":
        {
         "wall":null
        },
     "136":
        {
         "wall":null
        },
     "137":
        {
         "wall":null
        },
     "138":
        {
         "wall":true
        },
     "139":
        {
         "wall":null
        },
     "14":
        {
         "wall":null
        },
     "140":
        {
         "wall":null
        },
     "141":
        {
         "wall":true
        },
     "142":
        {
         "wall":null
        },
     "143":
        {
         "wall":null
        },
     "144":
        {
         "wall":null
        },
     "145":
        {
         "wall":null
        },
     "146":
        {
         "wall":null
        },
     "147":
        {
         "wall":null
        },
     "148":
        {
         "wall":true
        },
     "149":
        {
         "wall":null
        },
     "15":
        {
         "wall":null
        },
     "150":
        {
         "wall":null
        },
     "151":
        {
         "wall":null
        },
     "152":
        {
         "wall":null
        },
     "153":
        {
         "wall":null
        },
     "154":
        {
         "wall":null
        },
     "155":
        {
         "wall":null
        },
     "156":
        {
         "wall":null
        },
     "157":
        {
         "wall":null
        },
     "158":
        {
         "wall":true
        },
     "159":
        {
         "wall":null
        },
     "16":
        {
         "wall":null
        },
     "160":
        {
         "wall":null
        },
     "161":
        {
         "wall":true
        },
     "162":
        {
         "wall":null
        },
     "163":
        {
         "wall":null
        },
     "164":
        {
         "wall":null
        },
     "165":
        {
         "wall":null
        },
     "166":
        {
         "wall":null
        },
     "167":
        {
         "wall":null
        },
     "168":
        {
         "wall":true
        },
     "169":
        {
         "wall":null
        },
     "17":
        {
         "wall":null
        },
     "170":
        {
         "wall":null
        },
     "171":
        {
         "wall":null
        },
     "172":
        {
         "wall":null
        },
     "173":
        {
         "wall":null
        },
     "174":
        {
         "wall":null
        },
     "175":
        {
         "wall":null
        },
     "176":
        {
         "wall":null
        },
     "177":
        {
         "wall":null
        },
     "178":
        {
         "wall":true
        },
     "179":
        {
         "wall":null
        },
     "18":
        {
         "wall":null
        },
     "180":
        {
         "wall":null
        },
     "181":
        {
         "wall":true
        },
     "182":
        {
         "wall":null
        },
     "183":
        {
         "wall":null
        },
     "184":
        {
         "wall":null
        },
     "185":
        {
         "wall":null
        },
     "186":
        {
         "wall":null
        },
     "187":
        {
         "wall":null
        },
     "188":
        {
         "wall":true
        },
     "189":
        {
         "wall":null
        },
     "19":
        {
         "wall":null
        },
     "190":
        {
         "wall":null
        },
     "191":
        {
         "wall":null
        },
     "192":
        {
         "wall":null
        },
     "193":
        {
         "wall":null
        },
     "194":
        {
         "wall":null
        },
     "195":
        {
         "wall":null
        },
     "196":
        {
         "wall":null
        },
     "197":
        {
         "wall":null
        },
     "198":
        {
         "wall":true
        },
     "199":
        {
         "wall":null
        },
     "2":
        {
         "wall":null
        },
     "20":
        {
         "wall":null
        },
     "200":
        {
         "wall":null
        },
     "201":
        {
         "wall":true
        },
     "202":
        {
         "wall":null
        },
     "203":
        {
         "wall":null
        },
     "204":
        {
         "wall":null
        },
     "205":
        {
         "wall":null
        },
     "206":
        {
         "wall":null
        },
     "207":
        {
         "wall":null
        },
     "208":
        {
         "wall":true
        },
     "209":
        {
         "wall":null
        },
     "21":
        {
         "wall":true
        },
     "210":
        {
         "wall":null
        },
     "211":
        {
         "wall":null
        },
     "212":
        {
         "wall":null
        },
     "213":
        {
         "wall":null
        },
     "214":
        {
         "wall":null
        },
     "215":
        {
         "wall":null
        },
     "216":
        {
         "wall":null
        },
     "217":
        {
         "wall":null
        },
     "218":
        {
         "wall":true
        },
     "219":
        {
         "wall":null
        },
     "22":
        {
         "wall":true
        },
     "220":
        {
         "wall":null
        },
     "221":
        {
         "wall":true
        },
     "222":
        {
         "wall":null
        },
     "223":
        {
         "wall":null
        },
     "224":
        {
         "wall":null
        },
     "225":
        {
         "wall":null
        },
     "226":
        {
         "wall":null
        },
     "227":
        {
         "wall":null
        },
     "228":
        {
         "wall":true
        },
     "229":
        {
         "wall":null
        },
     "23":
        {
         "wall":true
        },
     "230":
        {
         "wall":null
        },
     "231":
        {
         "wall":null
        },
     "232":
        {
         "wall":null
        },
     "233":
        {
         "wall":null
        },
     "234":
        {
         "wall":null
        },
     "235":
        {
         "wall":null
        },
     "236":
        {
         "wall":null
        },
     "237":
        {
         "wall":null
        },
     "238":
        {
         "wall":true
        },
     "239":
        {
         "wall":null
        },
     "24":
        {
         "wall":true
        },
     "240":
        {
         "wall":null
        },
     "241":
        {
         "wall":true
        },
     "242":
        {
         "wall":null
        },
     "243":
        {
         "wall":null
        },
     "244":
        {
         "wall":null
        },
     "245":
        {
         "wall":null
        },
     "246":
        {
         "wall":null
        },
     "247":
        {
         "wall":null
        },
     "248":
        {
         "wall":true
        },
     "249":
        {
         "wall":null
        },
     "25":
        {
         "wall":true
        },
     "250":
        {
         "wall":null
        },
     "251":
        {
         "wall":null
        },
     "252":
        {
         "wall":null
        },
     "253":
        {
         "wall":null
        },
     "254":
        {
         "wall":null
        },
     "255":
        {
         "wall":null
        },
     "256":
        {
         "wall":null
        },
     "257":
        {
         "wall":null
        },
     "258":
        {
         "wall":true
        },
     "259":
        {
         "wall":null
        },
     "26":
        {
         "wall":true
        },
     "260":
        {
         "wall":null
        },
     "261":
        {
         "wall":true
        },
     "262":
        {
         "wall":null
        },
     "263":
        {
         "wall":null
        },
     "264":
        {
         "wall":null
        },
     "265":
        {
         "wall":null
        },
     "266":
        {
         "wall":true
        },
     "267":
        {
         "wall":true
        },
     "268":
        {
         "wall":true
        },
     "269":
        {
         "wall":true
        },
     "27":
        {
         "wall":true
        },
     "270":
        {
         "wall":true
        },
     "271":
        {
         "wall":true
        },
     "272":
        {
         "wall":true
        },
     "273":
        {
         "wall":true
        },
     "274":
        {
         "wall":true
        },
     "275":
        {
         "wall":true
        },
     "276":
        {
         "wall":true
        },
     "277":
        {
         "wall":true
        },
     "278":
        {
         "wall":true
        },
     "279":
        {
         "wall":null
        },
     "28":
        {
         "wall":true
        },
     "280":
        {
         "wall":null
        },
     "281":
        {
         "wall":null
        },
     "282":
        {
         "wall":null
        },
     "283":
        {
         "wall":null
        },
     "284":
        {
         "wall":null
        },
     "285":
        {
         "wall":null
        },
     "286":
        {
         "wall":null
        },
     "287":
        {
         "wall":null
        },
     "288":
        {
         "wall":null
        },
     "289":
        {
         "wall":null
        },
     "29":
        {
         "wall":true
        },
     "290":
        {
         "wall":null
        },
     "291":
        {
         "wall":null
        },
     "292":
        {
         "wall":null
        },
     "293":
        {
         "wall":null
        },
     "294":
        {
         "wall":null
        },
     "295":
        {
         "wall":null
        },
     "296":
        {
         "wall":null
        },
     "297":
        {
         "wall":null
        },
     "298":
        {
         "wall":null
        },
     "299":
        {
         "wall":null
        },
     "3":
        {
         "wall":null
        },
     "30":
        {
         "wall":true
        },
     "31":
        {
         "wall":true
        },
     "32":
        {
         "wall":true
        },
     "33":
        {
         "wall":true
        },
     "34":
        {
         "wall":true
        },
     "35":
        {
         "wall":true
        },
     "36":
        {
         "wall":true
        },
     "37":
        {
         "wall":true
        },
     "38":
        {
         "wall":true
        },
     "39":
        {
         "wall":null
        },
     "4":
        {
         "wall":null
        },
     "40":
        {
         "wall":null
        },
     "41":
        {
         "wall":true
        },
     "42":
        {
         "wall":null
        },
     "43":
        {
         "wall":null
        },
     "44":
        {
         "wall":null
        },
     "45":
        {
         "wall":null
        },
     "46":
        {
         "wall":null
        },
     "47":
        {
         "wall":null
        },
     "48":
        {
         "wall":null
        },
     "49":
        {
         "wall":null
        },
     "5":
        {
         "wall":null
        },
     "50":
        {
         "wall":null
        },
     "51":
        {
         "wall":null
        },
     "52":
        {
         "wall":null
        },
     "53":
        {
         "wall":null
        },
     "54":
        {
         "wall":null
        },
     "55":
        {
         "wall":null
        },
     "56":
        {
         "wall":null
        },
     "57":
        {
         "wall":null
        },
     "58":
        {
         "wall":true
        },
     "59":
        {
         "wall":null
        },
     "6":
        {
         "wall":null
        },
     "60":
        {
         "wall":null
        },
     "61":
        {
         "wall":true
        },
     "62":
        {
         "wall":null
        },
     "63":
        {
         "wall":null
        },
     "64":
        {
         "wall":null
        },
     "65":
        {
         "wall":null
        },
     "66":
        {
         "wall":null
        },
     "67":
        {
         "wall":null
        },
     "68":
        {
         "wall":null
        },
     "69":
        {
         "wall":null
        },
     "7":
        {
         "wall":null
        },
     "70":
        {
         "wall":null
        },
     "71":
        {
         "wall":null
        },
     "72":
        {
         "wall":null
        },
     "73":
        {
         "wall":null
        },
     "74":
        {
         "wall":null
        },
     "75":
        {
         "wall":null
        },
     "76":
        {
         "wall":null
        },
     "77":
        {
         "wall":null
        },
     "78":
        {
         "wall":true
        },
     "79":
        {
         "wall":null
        },
     "8":
        {
         "wall":null
        },
     "80":
        {
         "wall":null
        },
     "81":
        {
         "wall":true
        },
     "82":
        {
         "wall":null
        },
     "83":
        {
         "wall":null
        },
     "84":
        {
         "wall":true
        },
     "85":
        {
         "wall":null
        },
     "86":
        {
         "wall":null
        },
     "87":
        {
         "wall":null
        },
     "88":
        {
         "wall":null
        },
     "89":
        {
         "wall":null
        },
     "9":
        {
         "wall":null
        },
     "90":
        {
         "wall":null
        },
     "91":
        {
         "wall":null
        },
     "92":
        {
         "wall":null
        },
     "93":
        {
         "wall":null
        },
     "94":
        {
         "wall":null
        },
     "95":
        {
         "wall":null
        },
     "96":
        {
         "wall":null
        },
     "97":
        {
         "wall":null
        },
     "98":
        {
         "wall":true
        },
     "99":
        {
         "wall":null
        }
    },
 "tilepropertytypes":
    {
     "0":
        {
         "wall":""
        },
     "1":
        {
         "wall":""
        },
     "10":
        {
         "wall":""
        },
     "100":
        {
         "wall":""
        },
     "101":
        {
         "wall":"bool"
        },
     "102":
        {
         "wall":""
        },
     "103":
        {
         "wall":""
        },
     "104":
        {
         "wall":""
        },
     "105":
        {
         "wall":""
        },
     "106":
        {
         "wall":""
        },
     "107":
        {
         "wall":""
        },
     "108":
        {
         "wall":"bool"
        },
     "109":
        {
         "wall":""
        },
     "11":
        {
         "wall":""
        },
     "110":
        {
         "wall":""
        },
     "111":
        {
         "wall":""
        },
     "112":
        {
         "wall":""
        },
     "113":
        {
         "wall":""
        },
     "114":
        {
         "wall":""
        },
     "115":
        {
         "wall":""
        },
     "116":
        {
         "wall":""
        },
     "117":
        {
         "wall":""
        },
     "118":
        {
         "wall":"bool"
        },
     "119":
        {
         "wall":""
        },
     "12":
        {
         "wall":""
        },
     "120":
        {
         "wall":""
        },
     "121":
        {
         "wall":"bool"
        },
     "122":
        {
         "wall":""
        },
     "123":
        {
         "wall":""
        },
     "124":
        {
         "wall":""
        },
     "125":
        {
         "wall":""
        },
     "126":
        {
         "wall":""
        },
     "127":
        {
         "wall":""
        },
     "128":
        {
         "wall":"bool"
        },
     "129":
        {
         "wall":""
        },
     "13":
        {
         "wall":""
        },
     "130":
        {
         "wall":""
        },
     "131":
        {
         "wall":""
        },
     "132":
        {
         "wall":""
        },
     "133":
        {
         "wall":""
        },
     "134":
        {
         "wall":""
        },
     "135":
        {
         "wall":""
        },
     "136":
        {
         "wall":""
        },
     "137":
        {
         "wall":""
        },
     "138":
        {
         "wall":"bool"
        },
     "139":
        {
         "wall":""
        },
     "14":
        {
         "wall":""
        },
     "140":
        {
         "wall":""
        },
     "141":
        {
         "wall":"bool"
        },
     "142":
        {
         "wall":""
        },
     "143":
        {
         "wall":""
        },
     "144":
        {
         "wall":""
        },
     "145":
        {
         "wall":""
        },
     "146":
        {
         "wall":""
        },
     "147":
        {
         "wall":""
        },
     "148":
        {
         "wall":"bool"
        },
     "149":
        {
         "wall":""
        },
     "15":
        {
         "wall":""
        },
     "150":
        {
         "wall":""
        },
     "151":
        {
         "wall":""
        },
     "152":
        {
         "wall":""
        },
     "153":
        {
         "wall":""
        },
     "154":
        {
         "wall":""
        },
     "155":
        {
         "wall":""
        },
     "156":
        {
         "wall":""
        },
     "157":
        {
         "wall":""
        },
     "158":
        {
         "wall":"bool"
        },
     "159":
        {
         "wall":""
        },
     "16":
        {
         "wall":""
        },
     "160":
        {
         "wall":""
        },
     "161":
        {
         "wall":"bool"
        },
     "162":
        {
         "wall":""
        },
     "163":
        {
         "wall":""
        },
     "164":
        {
         "wall":""
        },
     "165":
        {
         "wall":""
        },
     "166":
        {
         "wall":""
        },
     "167":
        {
         "wall":""
        },
     "168":
        {
         "wall":"bool"
        },
     "169":
        {
         "wall":""
        },
     "17":
        {
         "wall":""
        },
     "170":
        {
         "wall":""
        },
     "171":
        {
         "wall":""
        },
     "172":
        {
         "wall":""
        },
     "173":
        {
         "wall":""
        },
     "174":
        {
         "wall":""
        },
     "175":
        {
         "wall":""
        },
     "176":
        {
         "wall":""
        },
     "177":
        {
         "wall":""
        },
     "178":
        {
         "wall":"bool"
        },
     "179":
        {
         "wall":""
        },
     "18":
        {
         "wall":""
        },
     "180":
        {
         "wall":""
        },
     "181":
        {
         "wall":"bool"
        },
     "182":
        {
         "wall":""
        },
     "183":
        {
         "wall":""
        },
     "184":
        {
         "wall":""
        },
     "185":
        {
         "wall":""
        },
     "186":
        {
         "wall":""
        },
     "187":
        {
         "wall":""
        },
     "188":
        {
         "wall":"bool"
        },
     "189":
        {
         "wall":""
        },
     "19":
        {
         "wall":""
        },
     "190":
        {
         "wall":""
        },
     "191":
        {
         "wall":""
        },
     "192":
        {
         "wall":""
        },
     "193":
        {
         "wall":""
        },
     "194":
        {
         "wall":""
        },
     "195":
        {
         "wall":""
        },
     "196":
        {
         "wall":""
        },
     "197":
        {
         "wall":""
        },
     "198":
        {
         "wall":"bool"
        },
     "199":
        {
         "wall":""
        },
     "2":
        {
         "wall":""
        },
     "20":
        {
         "wall":""
        },
     "200":
        {
         "wall":""
        },
     "201":
        {
         "wall":"bool"
        },
     "202":
        {
         "wall":""
        },
     "203":
        {
         "wall":""
        },
     "204":
        {
         "wall":""
        },
     "205":
        {
         "wall":""
        },
     "206":
        {
         "wall":""
        },
     "207":
        {
         "wall":""
        },
     "208":
        {
         "wall":"bool"
        },
     "209":
        {
         "wall":""
        },
     "21":
        {
         "wall":"bool"
        },
     "210":
        {
         "wall":""
        },
     "211":
        {
         "wall":""
        },
     "212":
        {
         "wall":""
        },
     "213":
        {
         "wall":""
        },
     "214":
        {
         "wall":""
        },
     "215":
        {
         "wall":""
        },
     "216":
        {
         "wall":""
        },
     "217":
        {
         "wall":""
        },
     "218":
        {
         "wall":"bool"
        },
     "219":
        {
         "wall":""
        },
     "22":
        {
         "wall":"bool"
        },
     "220":
        {
         "wall":""
        },
     "221":
        {
         "wall":"bool"
        },
     "222":
        {
         "wall":""
        },
     "223":
        {
         "wall":""
        },
     "224":
        {
         "wall":""
        },
     "225":
        {
         "wall":""
        },
     "226":
        {
         "wall":""
        },
     "227":
        {
         "wall":""
        },
     "228":
        {
         "wall":"bool"
        },
     "229":
        {
         "wall":""
        },
     "23":
        {
         "wall":"bool"
        },
     "230":
        {
         "wall":""
        },
     "231":
        {
         "wall":""
        },
     "232":
        {
         "wall":""
        },
     "233":
        {
         "wall":""
        },
     "234":
        {
         "wall":""
        },
     "235":
        {
         "wall":""
        },
     "236":
        {
         "wall":""
        },
     "237":
        {
         "wall":""
        },
     "238":
        {
         "wall":"bool"
        },
     "239":
        {
         "wall":""
        },
     "24":
        {
         "wall":"bool"
        },
     "240":
        {
         "wall":""
        },
     "241":
        {
         "wall":"bool"
        },
     "242":
        {
         "wall":""
        },
     "243":
        {
         "wall":""
        },
     "244":
        {
         "wall":""
        },
     "245":
        {
         "wall":""
        },
     "246":
        {
         "wall":""
        },
     "247":
        {
         "wall":""
        },
     "248":
        {
         "wall":"bool"
        },
     "249":
        {
         "wall":""
        },
     "25":
        {
         "wall":"bool"
        },
     "250":
        {
         "wall":""
        },
     "251":
        {
         "wall":""
        },
     "252":
        {
         "wall":""
        },
     "253":
        {
         "wall":""
        },
     "254":
        {
         "wall":""
        },
     "255":
        {
         "wall":""
        },
     "256":
        {
         "wall":""
        },
     "257":
        {
         "wall":""
        },
     "258":
        {
         "wall":"bool"
        },
     "259":
        {
         "wall":""
        },
     "26":
        {
         "wall":"bool"
        },
     "260":
        {
         "wall":""
        },
     "261":
        {
         "wall":"bool"
        },
     "262":
        {
         "wall":""
        },
     "263":
        {
         "wall":""
        },
     "264":
        {
         "wall":""
        },
     "265":
        {
         "wall":""
        },
     "266":
        {
         "wall":"bool"
        },
     "267":
        {
         "wall":"bool"
        },
     "268":
        {
         "wall":"bool"
        },
     "269":
        {
         "wall":"bool"
        },
     "27":
        {
         "wall":"bool"
        },
     "270":
        {
         "wall":"bool"
        },
     "271":
        {
         "wall":"bool"
        },
     "272":
        {
         "wall":"bool"
        },
     "273":
        {
         "wall":"bool"
        },
     "274":
        {
         "wall":"bool"
        },
     "275":
        {
         "wall":"bool"
        },
     "276":
        {
         "wall":"bool"
        },
     "277":
        {
         "wall":"bool"
        },
     "278":
        {
         "wall":"bool"
        },
     "279":
        {
         "wall":""
        },
     "28":
        {
         "wall":"bool"
        },
     "280":
        {
         "wall":""
        },
     "281":
        {
         "wall":""
        },
     "282":
        {
         "wall":""
        },
     "283":
        {
         "wall":""
        },
     "284":
        {
         "wall":""
        },
     "285":
        {
         "wall":""
        },
     "286":
        {
         "wall":""
        },
     "287":
        {
         "wall":""
        },
     "288":
        {
         "wall":""
        },
     "289":
        {
         "wall":""
        },
     "29":
        {
         "wall":"bool"
        },
     "290":
        {
         "wall":""
        },
     "291":
        {
         "wall":""
        },
     "292":
        {
         "wall":""
        },
     "293":
        {
         "wall":""
        },
     "294":
        {
         "wall":""
        },
     "295":
        {
         "wall":""
        },
     "296":
        {
         "wall":""
        },
     "297":
        {
         "wall":""
        },
     "298":
        {
         "wall":""
        },
     "299":
        {
         "wall":""
        },
     "3":
        {
         "wall":""
        },
     "30":
        {
         "wall":"bool"
        },
     "31":
        {
         "wall":"bool"
        },
     "32":
        {
         "wall":"bool"
        },
     "33":
        {
         "wall":"bool"
        },
     "34":
        {
         "wall":"bool"
        },
     "35":
        {
         "wall":"bool"
        },
     "36":
        {
         "wall":"bool"
        },
     "37":
        {
         "wall":"bool"
        },
     "38":
        {
         "wall":"bool"
        },
     "39":
        {
         "wall":""
        },
     "4":
        {
         "wall":""
        },
     "40":
        {
         "wall":""
        },
     "41":
        {
         "wall":"bool"
        },
     "42":
        {
         "wall":""
        },
     "43":
        {
         "wall":""
        },
     "44":
        {
         "wall":""
        },
     "45":
        {
         "wall":""
        },
     "46":
        {
         "wall":""
        },
     "47":
        {
         "wall":""
        },
     "48":
        {
         "wall":""
        },
     "49":
        {
         "wall":""
        },
     "5":
        {
         "wall":""
        },
     "50":
        {
         "wall":""
        },
     "51":
        {
         "wall":""
        },
     "52":
        {
         "wall":""
        },
     "53":
        {
         "wall":""
        },
     "54":
        {
         "wall":""
        },
     "55":
        {
         "wall":""
        },
     "56":
        {
         "wall":""
        },
     "57":
        {
         "wall":""
        },
     "58":
        {
         "wall":"bool"
        },
     "59":
        {
         "wall":""
        },
     "6":
        {
         "wall":""
        },
     "60":
        {
         "wall":""
        },
     "61":
        {
         "wall":"bool"
        },
     "62":
        {
         "wall":""
        },
     "63":
        {
         "wall":""
        },
     "64":
        {
         "wall":""
        },
     "65":
        {
         "wall":""
        },
     "66":
        {
         "wall":""
        },
     "67":
        {
         "wall":""
        },
     "68":
        {
         "wall":""
        },
     "69":
        {
         "wall":""
        },
     "7":
        {
         "wall":""
        },
     "70":
        {
         "wall":""
        },
     "71":
        {
         "wall":""
        },
     "72":
        {
         "wall":""
        },
     "73":
        {
         "wall":""
        },
     "74":
        {
         "wall":""
        },
     "75":
        {
         "wall":""
        },
     "76":
        {
         "wall":""
        },
     "77":
        {
         "wall":""
        },
     "78":
        {
         "wall":"bool"
        },
     "79":
        {
         "wall":""
        },
     "8":
        {
         "wall":""
        },
     "80":
        {
         "wall":""
        },
     "81":
        {
         "wall":"bool"
        },
     "82":
        {
         "wall":""
        },
     "83":
        {
         "wall":""
        },
     "84":
        {
         "wall":"bool"
        },
     "85":
        {
         "wall":""
        },
     "86":
        {
         "wall":""
        },
     "87":
        {
         "wall":""
        },
     "88":
        {
         "wall":""
        },
     "89":
        {
         "wall":""
        },
     "9":
        {
         "wall":""
        },
     "90":
        {
         "wall":""
        },
     "91":
        {
         "wall":""
        },
     "92":
        {
         "wall":""
        },
     "93":
        {
         "wall":""
        },
     "94":
        {
         "wall":""
        },
     "95":
        {
         "wall":""
        },
     "96":
        {
         "wall":""
        },
     "97":
        {
         "wall":""
        },
     "98":
        {
         "wall":"bool"
        },
     "99":
        {
         "wall":""
        }
    },
 "tilewidth":100,
 "transparentcolor":"#ff00ff",
 "type":"tileset"
}