{"scaleName":"web","variation":"EN","loadingStage":"work","id":"work_EN_web","resolution":1,"meta":{"type":"pixi-packer","version":"1","app":"https://github.com/gamevy/pixi-packer"},"spritesheets":[{"image":"cc949bbe762df9ffa9d3f3873385c22eb7e8075a.jpeg","filesize":122067,"sprites":[{"name":"tennis_court4","position":{"x":0,"y":0},"dimension":{"w":1129,"h":1334}}]},{"image":"81865d866eb7fa4f3b580a5093c40e53f9e86d33.jpeg","filesize":159489,"sprites":[{"name":"gravel_roof","position":{"x":0,"y":0},"dimension":{"w":840,"h":336}},{"name":"road_00","position":{"x":0,"y":337},"dimension":{"w":840,"h":84}},{"name":"BT01_ConcreteRoofGrunge_23","position":{"x":0,"y":422},"dimension":{"w":798,"h":504}},{"name":"sidewalk","position":{"x":0,"y":927},"dimension":{"w":552,"h":91}},{"name":"concrete_roof","position":{"x":799,"y":422},"dimension":{"w":504,"h":504}},{"name":"tar_roof","position":{"x":1304,"y":422},"dimension":{"w":336,"h":504}},{"name":"RT01_TarmacGrungeDash_25x40[Modern, city, map, Map tile, street, road, asphalt, paved, 2 lane, blacktop, seamless]","position":{"x":1641,"y":422},"dimension":{"w":210,"h":336}},{"name":"road_long","position":{"x":841,"y":0},"dimension":{"w":210,"h":336}},{"name":"wood_planks_vertical","position":{"x":1052,"y":0},"dimension":{"w":307,"h":307}},{"name":"cross_walk","position":{"x":553,"y":927},"dimension":{"w":210,"h":42}},{"name":"grass_tile","position":{"x":1641,"y":759},"dimension":{"w":165,"h":165}},{"name":"white_tiles","position":{"x":1807,"y":759},"dimension":{"w":150,"h":150}},{"name":"40113876-work-in-progress","position":{"x":1852,"y":422},"dimension":{"w":107,"h":60}},{"name":"seamless_concrete","position":{"x":1958,"y":759},"dimension":{"w":90,"h":90}},{"name":"wood_floor","position":{"x":1852,"y":483},"dimension":{"w":84,"h":84}},{"name":"tile_floor","position":{"x":1852,"y":568},"dimension":{"w":84,"h":84}},{"name":"MI01_FurnitureShower_05x10[shower, standing shower, shower stall, bathroom, water closet]","position":{"x":553,"y":970},"dimension":{"w":84,"h":42}},{"name":"tile_concrete","position":{"x":1852,"y":653},"dimension":{"w":84,"h":84}},{"name":"white_square","position":{"x":1937,"y":653},"dimension":{"w":77,"h":77}}]},{"image":"04a71c1726a1f0c260ba8cfd71078ec8499178b3.jpeg","filesize":22303,"sprites":[{"name":"road","position":{"x":0,"y":0},"dimension":{"w":306,"h":612}}]}]}