{"scaleName":"web","variation":"EN","loadingStage":"work","id":"work_EN_web","resolution":0.3,"meta":{"type":"pixi-packer","version":"1","app":"https://github.com/gamevy/pixi-packer"},"spritesheets":[{"image":"a6d72537ecc14ea86f740c5b59d53cb7097fbc03.jpeg","filesize":156778,"sprites":[{"name":"road_00","position":{"x":0,"y":0},"dimension":{"w":840,"h":84}},{"name":"gravel_roof","position":{"x":0,"y":85},"dimension":{"w":840,"h":336}},{"name":"BT01_ConcreteRoofGrunge_23","position":{"x":0,"y":422},"dimension":{"w":798,"h":504}},{"name":"concrete_roof","position":{"x":0,"y":927},"dimension":{"w":504,"h":504}},{"name":"tar_roof","position":{"x":0,"y":1432},"dimension":{"w":336,"h":504}},{"name":"road_long","position":{"x":337,"y":1432},"dimension":{"w":210,"h":336}},{"name":"RT01_TarmacGrungeDash_25x40[Modern, city, map, Map tile, street, road, asphalt, paved, 2 lane, blacktop, seamless]","position":{"x":548,"y":1432},"dimension":{"w":210,"h":336}},{"name":"wood_planks_vertical","position":{"x":759,"y":1432},"dimension":{"w":307,"h":307}},{"name":"cross_walk","position":{"x":0,"y":1937},"dimension":{"w":210,"h":42}},{"name":"carpet_floor","position":{"x":1067,"y":1432},"dimension":{"w":168,"h":168}},{"name":"grass_tile","position":{"x":337,"y":1769},"dimension":{"w":165,"h":165}},{"name":"white_tiles","position":{"x":503,"y":1769},"dimension":{"w":150,"h":150}},{"name":"40113876-work-in-progress","position":{"x":0,"y":1980},"dimension":{"w":107,"h":60}},{"name":"seamless_concrete","position":{"x":654,"y":1769},"dimension":{"w":90,"h":90}},{"name":"tile_concrete","position":{"x":745,"y":1769},"dimension":{"w":84,"h":84}},{"name":"tile_floor","position":{"x":830,"y":1769},"dimension":{"w":84,"h":84}},{"name":"wood_floor","position":{"x":915,"y":1769},"dimension":{"w":84,"h":84}},{"name":"white_square","position":{"x":1000,"y":1769},"dimension":{"w":77,"h":77}}]}]}